flygym/__init__.py
flygym/arena/__init__.py
flygym/arena/base.py
flygym/arena/complex_terrain.py
flygym/arena/sensory_environment.py
flygym/arena/tethered.py
flygym/camera.py
flygym/config.yaml
flygym/core.py
flygym/data/behavior/210902_pr_fly1.pkl
flygym/data/behavior/contact_mask.csv
flygym/data/behavior/position_data.csv
flygym/data/behavior/single_steps_untethered.pkl
flygym/data/etc/locomotion_icons/forward.png
flygym/data/etc/locomotion_icons/left.png
flygym/data/etc/locomotion_icons/right.png
flygym/data/etc/locomotion_icons/stop.png
flygym/data/mesh/A1A2.stl
flygym/data/mesh/A3.stl
flygym/data/mesh/A4.stl
flygym/data/mesh/A5.stl
flygym/data/mesh/A6.stl
flygym/data/mesh/Haustellum.stl
flygym/data/mesh/Head.stl
flygym/data/mesh/LAntenna.stl
flygym/data/mesh/LArista.stl
flygym/data/mesh/LEye.stl
flygym/data/mesh/LFCoxa.stl
flygym/data/mesh/LFFemur.stl
flygym/data/mesh/LFTarsus1.stl
flygym/data/mesh/LFTarsus2.stl
flygym/data/mesh/LFTarsus3.stl
flygym/data/mesh/LFTarsus4.stl
flygym/data/mesh/LFTarsus5.stl
flygym/data/mesh/LFTibia.stl
flygym/data/mesh/LFuniculus.stl
flygym/data/mesh/LHCoxa.stl
flygym/data/mesh/LHFemur.stl
flygym/data/mesh/LHTarsus1.stl
flygym/data/mesh/LHTarsus2.stl
flygym/data/mesh/LHTarsus3.stl
flygym/data/mesh/LHTarsus4.stl
flygym/data/mesh/LHTarsus5.stl
flygym/data/mesh/LHTibia.stl
flygym/data/mesh/LHaltere.stl
flygym/data/mesh/LMCoxa.stl
flygym/data/mesh/LMFemur.stl
flygym/data/mesh/LMTarsus1.stl
flygym/data/mesh/LMTarsus2.stl
flygym/data/mesh/LMTarsus3.stl
flygym/data/mesh/LMTarsus4.stl
flygym/data/mesh/LMTarsus5.stl
flygym/data/mesh/LMTibia.stl
flygym/data/mesh/LPedicel.stl
flygym/data/mesh/LWing.stl
flygym/data/mesh/RAntenna.stl
flygym/data/mesh/RArista.stl
flygym/data/mesh/REye.stl
flygym/data/mesh/RFCoxa.stl
flygym/data/mesh/RFFemur.stl
flygym/data/mesh/RFTarsus1.stl
flygym/data/mesh/RFTarsus2.stl
flygym/data/mesh/RFTarsus3.stl
flygym/data/mesh/RFTarsus4.stl
flygym/data/mesh/RFTarsus5.stl
flygym/data/mesh/RFTibia.stl
flygym-1.2.1.dist-info/LICENSE
flygym-1.2.1.dist-info/METADATA
flygym-1.2.1.dist-info/WHEEL
flygym-1.2.1.dist-info/RECORD
