Metadata-Version: 2.3
Name: flygym
Version: 1.2.1
Summary: Implementation of NeuroMechFly v2, a framework for simulating embodied sensorimotor control in adult Drosophila.
License: Apache-2.0
Author: Sibo Wang-Chen
Author-email: sibo.wang@epfl.ch
Maintainer: Sibo Wang-Chen
Maintainer-email: sibo.wang@epfl.ch
Requires-Python: >=3.10,<3.13
Classifier: License :: OSI Approved :: Apache Software License
Classifier: Programming Language :: Python :: 3
Classifier: Programming Language :: Python :: 3.10
Classifier: Programming Language :: Python :: 3.11
Classifier: Programming Language :: Python :: 3.12
Provides-Extra: dev
Provides-Extra: examples
Requires-Dist: black[jupyter] (==23.3.0) ; extra == "dev"
Requires-Dist: build (>=1.2,<2.0) ; extra == "dev"
Requires-Dist: dm_control (==1.0.27)
Requires-Dist: dm_tree (==0.1.8)
Requires-Dist: flyvis (==1.1.2) ; extra == "examples"
Requires-Dist: furo ; extra == "dev"
Requires-Dist: gymnasium
Requires-Dist: h5py (>=3.0,<4.0) ; extra == "examples"
Requires-Dist: imageio[ffmpeg,pyav] (>=2.0,<3.0)
Requires-Dist: joblib (>=1.0,<2.0) ; extra == "examples"
Requires-Dist: jupyter (>=1.0,<2.0)
Requires-Dist: lightning (>=2.0,<3.0) ; extra == "examples"
Requires-Dist: mediapy (>=1.0,<2.0)
Requires-Dist: mujoco (==3.2.7)
Requires-Dist: networkx (>=3.0,<4.0) ; extra == "examples"
Requires-Dist: numba (==0.60.0)
Requires-Dist: numpy (>=2.0,<3.0)
Requires-Dist: numpydoc (>=1.0,<2.0) ; extra == "dev"
Requires-Dist: opencv-python (>=4.0,<5.0)
Requires-Dist: pandas (>=2.0,<3.0) ; extra == "examples"
Requires-Dist: phiflow (>=3.3.0,<4.0) ; extra == "examples"
Requires-Dist: phiml (>=1.12.0,<2.0) ; extra == "examples"
Requires-Dist: pytest (>=8.0,<9.0) ; extra == "dev"
Requires-Dist: pyyaml (>=6.0,<7.0)
Requires-Dist: rasterio (>=1.0,<2.0) ; extra == "dev"
Requires-Dist: requests (>=2.0,<3.0) ; extra == "dev"
Requires-Dist: ruff (==0.9.4) ; extra == "dev"
Requires-Dist: scikit-learn (>=1.0,<2.0) ; extra == "examples"
Requires-Dist: scipy (>=1.0,<2.0)
Requires-Dist: seaborn (==0.13) ; extra == "examples"
Requires-Dist: shapely (>=2.0,<3.0) ; extra == "dev"
Requires-Dist: sphinx (>=8.0,<9.0) ; extra == "dev"
Requires-Dist: sphinxcontrib-googleanalytics (==0.4) ; extra == "dev"
Requires-Dist: tensorboardX (>=2.0,<3.0) ; extra == "examples"
Requires-Dist: torch (>=2.0,<3.0) ; extra == "examples"
Requires-Dist: tqdm (>=4.0,<5.0)
Project-URL: Bug Tracker, https://github.com/NeLy-EPFL/flygym/issues
Project-URL: Documentation, https://neuromechfly.org/
Project-URL: Homepage, https://neuromechfly.org/
Project-URL: Repository, https://github.com/NeLy-EPFL/flygym
